typicle/__init__.py
typicle/_version.py
typicle/convert.py
typicle/types.yml
typicle-0.1.4.dist-info/LICENSE.txt
typicle-0.1.4.dist-info/METADATA
typicle-0.1.4.dist-info/WHEEL
typicle-0.1.4.dist-info/top_level.txt
typicle-0.1.4.dist-info/RECORD
