Metadata-Version: 2.1
Name: typicle
Version: 0.1.4
Summary: Consistent data types for particle physics data.
Home-page: https://github.com/jacanchaplais/typicle
Author: Jacan Chaplais
Author-email: jacanchaplais@gmail.com
License: BSD 3-Clause License
Platform: UNKNOWN
Classifier: Programming Language :: Python :: 3
Classifier: License :: OSI Approved :: BSD License
Classifier: Operating System :: OS Independent
License-File: LICENSE.txt
Requires-Dist: pyyaml
